rtl/baud.v
// Baud Rate Generator (16x Oversampling Clock Enable)
module baud #(
    parameter CLK_freq  = 50000000, // 50 MHz default
    parameter BAUD_RATE = 115200    // Target Baud Rate
)(
    input  wire clk,   // System clock
    input  wire rst, // Active-low asynchronous reset
    output wire tick   // 16x Baud tick pulse
);

    // Calculate count threshold M = CLK_freq / (16 * BAUD_RATE)
    localparam M = CLK_freq / (16 * BAUD_RATE);
    localparam COUNTER_WIDTH = $clog2(M);

    reg [COUNTER_WIDTH-1:0] count_reg;

    always @(posedge clk or negedge rst) begin
        if (!rst) 
        begin
            count_reg <= {COUNTER_WIDTH{1'b0}};
        end 
        else begin
            if (count_reg == M - 1)
                count_reg <= {COUNTER_WIDTH{1'b0}};
            else
                count_reg <= count_reg + 1'b1;
        end
    end

    // Tick pulse goes HIGH for exactly one clock period when count reaches M-1
    assign tick = (count_reg == M - 1);

endmodule

testbenches/baud_tb.v
`timescale 1ns/1ps

module baud_tb;

    reg clk = 0;
    reg rst;
    wire tick;

    // Instantiate with smaller parameters for fast simulation viewing
    // M = 50000000 / (16 * 115200) = 27 clock ticks per baud pulse
    baud #(
        .CLK_freq(50000000),
        .BAUD_RATE(115200)
    ) uut (
        .clk(clk),
        .rst(rst),
        .tick(tick)
    );

    // 50MHz clock generation 
    always #10 clk = ~clk;

    initial begin
        // --- GTKWave VCD Setup ---
        $dumpfile("baud_gen.vcd");
        $dumpvars(0, baud_tb);

        // --- Test Sequence ---
        rst = 0;

        // Apply Reset
        #20 rst = 1;

        // Run simulation long enough to capture multiple tick pulses
        #2000;

        $display("Simulation complete. Open GTKWave to inspect baud_gen.vcd");
        $finish;
    end

endmodule

sim/baud_gen.vcd
$date
	Sat Sep 19 20:46:34 2026
$end
$version
	Icarus Verilog
$end
$timescale
	1ps
$end
$scope module baud_tb $end
$var wire 1 ! tick $end
$var reg 1 " clk $end
$var reg 1 # rst $end
$scope module uut $end
$var wire 1 " clk $end
$var wire 1 # rst $end
$var wire 1 ! tick $end
$var parameter 32 $ BAUD_RATE $end
$var parameter 32 % CLK_freq $end
$var parameter 32 & COUNTER_WIDTH $end
$var parameter 64 ' M $end
$var reg 5 ( count_reg [4:0] $end
$upscope $end
$upscope $end
$enddefinitions $end
$comment Show the parameter values. $end
$dumpall
b11011 '
b101 &
b10111110101111000010000000 %
b11100001000000000 $
$end
#0
$dumpvars
b0 (
0#
0"
0!
$end
#10000
1"
#20000
0"
1#
#30000
b1 (
1"
#40000
0"
#50000
b10 (
1"
#60000
0"
#70000
b11 (
1"
#80000
0"
#90000
b100 (
1"
#100000
0"
#110000
b101 (
1"
#120000
0"
#130000
b110 (
1"
#140000
0"
#150000
b111 (
1"
#160000
0"
#170000
b1000 (
1"
#180000
0"
#190000
b1001 (
1"
#200000
0"
#210000
b1010 (
1"
#220000
0"
#230000
b1011 (
1"
#240000
0"
#250000
b1100 (
1"
#260000
0"
#270000
b1101 (
1"
#280000
0"
#290000
b1110 (
1"
#300000
0"
#310000
b1111 (
1"
#320000
0"
#330000
b10000 (
1"
#340000
0"
#350000
b10001 (
1"
#360000
0"
#370000
b10010 (
1"
#380000
0"
#390000
b10011 (
1"
#400000
0"
#410000
b10100 (
1"
#420000
0"
#430000
b10101 (
1"
#440000
0"
#450000
b10110 (
1"
#460000
0"
#470000
b10111 (
1"
#480000
0"
#490000
b11000 (
1"
#500000
0"
#510000
b11001 (
1"
#520000
0"
#530000
1!
b11010 (
1"
#540000
0"
#550000
0!
b0 (
1"
#560000
0"
#570000
b1 (
1"
#580000
0"
#590000
b10 (
1"
#600000
0"
#610000
b11 (
1"
#620000
0"
#630000
b100 (
1"
#640000
0"
#650000
b101 (
1"
#660000
0"
#670000
b110 (
1"
#680000
0"
#690000
b111 (
1"
#700000
0"
#710000
b1000 (
1"
#720000
0"
#730000
b1001 (
1"
#740000
0"
#750000
b1010 (
1"
#760000
0"
#770000
b1011 (
1"
#780000
0"
#790000
b1100 (
1"
#800000
0"
#810000
b1101 (
1"
#820000
0"
#830000
b1110 (
1"
#840000
0"
#850000
b1111 (
1"
#860000
0"
#870000
b10000 (
1"
#880000
0"
#890000
b10001 (
1"
#900000
0"
#910000
b10010 (
1"
#920000
0"
#930000
b10011 (
1"
#940000
0"
#950000
b10100 (
1"
#960000
0"
#970000
b10101 (
1"
#980000
0"
#990000
b10110 (
1"
#1000000
0"
#1010000
b10111 (
1"
#1020000
0"
#1030000
b11000 (
1"
#1040000
0"
#1050000
b11001 (
1"
#1060000
0"
#1070000
1!
b11010 (
1"
#1080000
0"
#1090000
0!
b0 (
1"
#1100000
0"
#1110000
b1 (
1"
#1120000
0"
#1130000
b10 (
1"
#1140000
0"
#1150000
b11 (
1"
#1160000
0"
#1170000
b100 (
1"
#1180000
0"
#1190000
b101 (
1"
#1200000
0"
#1210000
b110 (
1"
#1220000
0"
#1230000
b111 (
1"
#1240000
0"
#1250000
b1000 (
1"
#1260000
0"
#1270000
b1001 (
1"
#1280000
0"
#1290000
b1010 (
1"
#1300000
0"
#1310000
b1011 (
1"
#1320000
0"
#1330000
b1100 (
1"
#1340000
0"
#1350000
b1101 (
1"
#1360000
0"
#1370000
b1110 (
1"
#1380000
0"
#1390000
b1111 (
1"
#1400000
0"
#1410000
b10000 (
1"
#1420000
0"
#1430000
b10001 (
1"
#1440000
0"
#1450000
b10010 (
1"
#1460000
0"
#1470000
b10011 (
1"
#1480000
0"
#1490000
b10100 (
1"
#1500000
0"
#1510000
b10101 (
1"
#1520000
0"
#1530000
b10110 (
1"
#1540000
0"
#1550000
b10111 (
1"
#1560000
0"
#1570000
b11000 (
1"
#1580000
0"
#1590000
b11001 (
1"
#1600000
0"
#1610000
1!
b11010 (
1"
#1620000
0"
#1630000
0!
b0 (
1"
#1640000
0"
#1650000
b1 (
1"
#1660000
0"
#1670000
b10 (
1"
#1680000
0"
#1690000
b11 (
1"
#1700000
0"
#1710000
b100 (
1"
#1720000
0"
#1730000
b101 (
1"
#1740000
0"
#1750000
b110 (
1"
#1760000
0"
#1770000
b111 (
1"
#1780000
0"
#1790000
b1000 (
1"
#1800000
0"
#1810000
b1001 (
1"
#1820000
0"
#1830000
b1010 (
1"
#1840000
0"
#1850000
b1011 (
1"
#1860000
0"
#1870000
b1100 (
1"
#1880000
0"
#1890000
b1101 (
1"
#1900000
0"
#1910000
b1110 (
1"
#1920000
0"
#1930000
b1111 (
1"
#1940000
0"
#1950000
b10000 (
1"
#1960000
0"
#1970000
b10001 (
1"
#1980000
0"
#1990000
b10010 (
1"
#2000000
0"
#2010000
b10011 (
1"
