rtl/uart_rx.v
/*

Title: UART RX module
Designer: Guerrout adem
Affiliation: University of Blida 1 - CDTA

UART Information:
  Baudrate: 115200
  Frame shape: 1'b start | 8'b data LSB first | 1'b stop
  Parity: N/A
*/



module uart_rx (
   input wire clk,
   input wire rst,
   input wire rx,
   input wire tick,
   output reg [7:0] rx_data,
   output reg rx_done
);
   // states encoding
   localparam IDLE = 2'b00;
   localparam START = 2'b01;
   localparam DATA = 2'b10;
   localparam STOP = 2'b11;
   reg [1:0] state;
   
   //internal counters
   
   reg [3:0] tick_reg;
   reg [2:0] bit_reg;
   reg [7:0] data_reg;
   
   reg rx_sync1 , rx_sync2;
   
   always @(posedge clk or negedge rst )
   begin
   if (!rst) begin 
      rx_sync1 <= 1'b1;
      rx_sync2 <= 1'b1;
   end 
   else begin
      rx_sync1 <=rx;
      rx_sync2 <=rx_sync1;
   end
   end
   
   // FSM State Register & Next State Logic
    always @(posedge clk or negedge rst) begin
        if (!rst) begin
            state    <= IDLE;
            tick_reg <= 4'b0;
            bit_reg  <= 3'b0;
            data_reg <= 8'b0;
            rx_data  <= 8'b0;
            rx_done  <= 1'b0;
        end else begin
            // Default: rx_done is a 1-cycle pulse, so clear it every clock cycle
            rx_done <= 1'b0;

        case (state)
                // IDLE: Wait for start bit
             IDLE: begin
                    if (rx_sync2 == 1'b0) begin
                        state    <= START;
                        tick_reg <= 4'b0;
                    end
                end
                //START: take midpoint of start bit
             START: begin
                    if (tick) begin
                        if (tick_reg == 4'd7) begin
                            state    <= DATA;
                            tick_reg <= 4'b0;
                            bit_reg  <= 3'b0; // Reset bit counter (0 to 7)
                        end else begin
                            tick_reg <= tick_reg + 1'b1;
                        end
                    end
                end

                //DATA: Sample 8 data bits, each 16 ticks 
             DATA: begin
                    if (tick) begin
                        if (tick_reg == 4'd15) begin
                            tick_reg <= 4'b0;
                            
                            // Shift incoming bit into MSB (LSB received first)
                            data_reg <= {rx_sync2, data_reg[7:1]};

                            if (bit_reg == 3'd7) begin
                                state <= STOP; // Received all 8 bits
                            end else begin
                                bit_reg <= bit_reg + 1'b1;
                            end
                        end else begin
                            tick_reg <= tick_reg + 1'b1;
                        end
                    end
                end

                // STOP: Wait 16 ticks for the stop bit
             STOP: begin
                    if (tick) begin
                        if (tick_reg == 4'd15) begin
                            state   <= IDLE;      // Back to IDLE
                            rx_data <= data_reg;  // Output final byte
                            rx_done <= 1'b1;      // Flag data ready!
                        end else begin
                            tick_reg <= tick_reg + 1'b1;
                        end
                    end
                end

                default: state <= IDLE;
            endcase
        end
    end
endmodule

testbenches/uart_rx_tb.v
/*

Title: UART RX module testbunch
Designer: Guerrout adem
Affiliation: University of Blida 1 - CDTA

UART Information:
  Baudrate: 115200
  Frame shape: 1'b start | 8'b data LSB first | 1'b stop
  Parity: N/A
*/


`timescale 1ns/1ps

module uart_rx_alone_tb;

    //Inputs to uut 
    reg clk = 0;
    reg rst = 0;
    reg rx  = 1; // Idle state
    reg tick = 0;

    //Outputs from uut
    wire [7:0] rx_data;
    wire rx_done;

    //50MHz clk
    always #10 clk = ~clk;

  
    uart_rx uut (
        .clk(clk),
        .rst(rst),
        .rx(rx),
        .tick(tick),
        .rx_data(rx_data),
        .rx_done(rx_done)
    );

    // Generates a 1-clock-cycle pulse every 160ns to simulate 'tick'
    always begin
        #140;
        tick = 1;
        #20; 
        tick = 0;
    end

    //  Task to Send 1 Serial Bit (Holds 'rx' for 16 ticks)
    task send_bit(input bit_val);
        integer i;
        begin
            rx = bit_val;
            for (i = 0; i < 16; i = i + 1) begin
                @(posedge tick); // Wait for the next tick pulse
            end
        end
    endtask

    // --- Test Sequence ---
    initial begin
        // Setup GTKWave dump file
        $dumpfile("rx_alone.vcd");
        $dumpvars(0, uart_rx_alone_tb);

        // Reset
        rst = 0;
        #40 rst = 1;
        #100;

        $display("[%0t ns] --- Test 1: Sending ASCII 'A' (0x41) ---", $time);

        // 1. Start Bit (0)
        send_bit(0);

        // 2. 8 Data Bits (LSB First for 0x41 = 8'b01000001)
        send_bit(1); // Bit 0 (LSB)
        send_bit(0); 
        send_bit(0); 
        send_bit(0); 
        send_bit(0); 
        send_bit(0); 
        send_bit(1); 
        send_bit(0); // Bit 7 (MSB)

        // 3. Stop Bit (1)
        send_bit(1);

        // Idle time between frames
        #1000;

        $display("[%0t ns] Simulation finished successfully!", $time);
        $finish;
    end

    // --- Self-Checking Monitor ---
    always @(posedge clk) begin
        if (rx_done) begin
            $display("[%0t ns] SUCCESS: Received Byte = 0x%h ('%c')", $time, rx_data, rx_data);
        end
    end

endmodule

sim/rx_alone.vcd
$date
	Sun Sep 20 11:50:35 2026
$end
$version
	Icarus Verilog
$end
$timescale
	1ps
$end
$scope module uart_rx_alone_tb $end
$var wire 1 ! rx_done $end
$var wire 8 " rx_data [7:0] $end
$var reg 1 # clk $end
$var reg 1 $ rst $end
$var reg 1 % rx $end
$var reg 1 & tick $end
$scope module uut $end
$var wire 1 # clk $end
$var wire 1 $ rst $end
$var wire 1 % rx $end
$var wire 1 & tick $end
$var parameter 2 ' DATA $end
$var parameter 2 ( IDLE $end
$var parameter 2 ) START $end
$var parameter 2 * STOP $end
$var reg 3 + bit_reg [2:0] $end
$var reg 8 , data_reg [7:0] $end
$var reg 8 - rx_data [7:0] $end
$var reg 1 ! rx_done $end
$var reg 1 . rx_sync1 $end
$var reg 1 / rx_sync2 $end
$var reg 2 0 state [1:0] $end
$var reg 4 1 tick_reg [3:0] $end
$upscope $end
$scope task send_bit $end
$var reg 1 2 bit_val $end
$var integer 32 3 i [31:0] $end
$upscope $end
$upscope $end
$enddefinitions $end
$comment Show the parameter values. $end
$dumpall
b11 *
b1 )
b0 (
b10 '
$end
#0
$dumpvars
bx 3
x2
b0 1
b0 0
1/
1.
b0 -
b0 ,
b0 +
0&
1%
0$
0#
b0 "
0!
$end
#10000
1#
#20000
0#
#30000
1#
#40000
0#
1$
#50000
1#
#60000
0#
#70000
1#
#80000
0#
#90000
1#
#100000
0#
#110000
1#
#120000
0#
#130000
1#
#140000
0#
b0 3
0%
02
1&
#150000
0.
1#
#160000
0#
0&
#170000
0/
1#
#180000
0#
#190000
b1 0
1#
#200000
0#
#210000
1#
#220000
0#
#230000
1#
#240000
0#
#250000
1#
#260000
0#
#270000
1#
#280000
0#
#290000
1#
#300000
b1 3
0#
1&
#310000
b1 1
1#
#320000
0#
0&
#330000
1#
#340000
0#
#350000
1#
#360000
0#
#370000
1#
#380000
0#
#390000
1#
#400000
0#
#410000
1#
#420000
0#
#430000
1#
#440000
0#
#450000
1#
#460000
b10 3
0#
1&
#470000
b10 1
1#
#480000
0#
0&
#490000
1#
#500000
0#
#510000
1#
#520000
0#
#530000
1#
#540000
0#
#550000
1#
#560000
0#
#570000
1#
#580000
0#
#590000
1#
#600000
0#
#610000
1#
#620000
b11 3
0#
1&
#630000
b11 1
1#
#640000
0#
0&
#650000
1#
#660000
0#
#670000
1#
#680000
0#
#690000
1#
#700000
0#
#710000
1#
#720000
0#
#730000
1#
#740000
0#
#750000
1#
#760000
0#
#770000
1#
#780000
b100 3
0#
1&
#790000
b100 1
1#
#800000
0#
0&
#810000
1#
#820000
0#
#830000
1#
#840000
0#
#850000
1#
#860000
0#
#870000
1#
#880000
0#
#890000
1#
#900000
0#
#910000
1#
#920000
0#
#930000
1#
#940000
b101 3
0#
1&
#950000
b101 1
1#
#960000
0#
0&
#970000
1#
#980000
0#
#990000
1#
#1000000
0#
#1010000
1#
#1020000
0#
#1030000
1#
#1040000
0#
#1050000
1#
#1060000
0#
#1070000
1#
#1080000
0#
#1090000
1#
#1100000
b110 3
0#
1&
#1110000
b110 1
1#
#1120000
0#
0&
#1130000
1#
#1140000
0#
#1150000
1#
#1160000
0#
#1170000
1#
#1180000
0#
#1190000
1#
#1200000
0#
#1210000
1#
#1220000
0#
#1230000
1#
#1240000
0#
#1250000
1#
#1260000
b111 3
0#
1&
#1270000
b111 1
1#
#1280000
0#
0&
#1290000
1#
#1300000
0#
#1310000
1#
#1320000
0#
#1330000
1#
#1340000
0#
#1350000
1#
#1360000
0#
#1370000
1#
#1380000
0#
#1390000
1#
#1400000
0#
#1410000
1#
#1420000
b1000 3
0#
1&
#1430000
b0 1
b10 0
1#
#1440000
0#
0&
#1450000
1#
#1460000
0#
#1470000
1#
#1480000
0#
#1490000
1#
#1500000
0#
#1510000
1#
#1520000
0#
#1530000
1#
#1540000
0#
#1550000
1#
#1560000
0#
#1570000
1#
#1580000
b1001 3
0#
1&
#1590000
b1 1
1#
#1600000
0#
0&
#1610000
1#
#1620000
0#
#1630000
1#
#1640000
0#
#1650000
1#
#1660000
0#
#1670000
1#
#1680000
0#
#1690000
1#
#1700000
0#
#1710000
1#
#1720000
0#
#1730000
1#
#1740000
b1010 3
0#
1&
#1750000
b10 1
1#
#1760000
0#
0&
#1770000
1#
#1780000
0#
#1790000
1#
#1800000
0#
#1810000
1#
#1820000
0#
#1830000
1#
#1840000
0#
#1850000
1#
#1860000
0#
#1870000
1#
#1880000
0#
#1890000
1#
#1900000
b1011 3
0#
1&
#1910000
b11 1
1#
#1920000
0#
0&
#1930000
1#
#1940000
0#
#1950000
1#
#1960000
0#
#1970000
1#
#1980000
0#
#1990000
1#
#2000000
0#
#2010000
1#
#2020000
0#
#2030000
1#
#2040000
0#
#2050000
1#
#2060000
b1100 3
0#
1&
#2070000
b100 1
1#
#2080000
0#
0&
#2090000
1#
#2100000
0#
#2110000
1#
#2120000
0#
#2130000
1#
#2140000
0#
#2150000
1#
#2160000
0#
#2170000
1#
#2180000
0#
#2190000
1#
#2200000
0#
#2210000
1#
#2220000
b1101 3
0#
1&
#2230000
b101 1
1#
#2240000
0#
0&
#2250000
1#
#2260000
0#
#2270000
1#
#2280000
0#
#2290000
1#
#2300000
0#
#2310000
1#
#2320000
0#
#2330000
1#
#2340000
0#
#2350000
1#
#2360000
0#
#2370000
1#
#2380000
b1110 3
0#
1&
#2390000
b110 1
1#
#2400000
0#
0&
#2410000
1#
#2420000
0#
#2430000
1#
#2440000
0#
#2450000
1#
#2460000
0#
#2470000
1#
#2480000
0#
#2490000
1#
#2500000
0#
#2510000
1#
#2520000
0#
#2530000
1#
#2540000
b1111 3
0#
1&
#2550000
b111 1
1#
#2560000
0#
0&
#2570000
1#
#2580000
0#
#2590000
1#
#2600000
0#
#2610000
1#
#2620000
0#
#2630000
1#
#2640000
0#
#2650000
1#
#2660000
0#
#2670000
1#
#2680000
0#
#2690000
1#
#2700000
1%
12
b0 3
0#
1&
#2710000
1.
b1000 1
1#
#2720000
0#
0&
#2730000
1/
1#
#2740000
0#
#2750000
1#
#2760000
0#
#2770000
1#
#2780000
0#
#2790000
1#
#2800000
0#
#2810000
1#
#2820000
0#
#2830000
1#
#2840000
0#
#2850000
1#
#2860000
b1 3
0#
1&
#2870000
b1001 1
1#
#2880000
0#
0&
#2890000
1#
#2900000
0#
#2910000
1#
#2920000
0#
#2930000
1#
#2940000
0#
#2950000
1#
#2960000
0#
#2970000
1#
#2980000
0#
#2990000
1#
#3000000
0#
#3010000
1#
#3020000
b10 3
0#
1&
#3030000
b1010 1
1#
#3040000
0#
0&
#3050000
1#
#3060000
0#
#3070000
1#
#3080000
0#
#3090000
1#
#3100000
0#
#3110000
1#
#3120000
0#
#3130000
1#
#3140000
0#
#3150000
1#
#3160000
0#
#3170000
1#
#3180000
b11 3
0#
1&
#3190000
b1011 1
1#
#3200000
0#
0&
#3210000
1#
#3220000
0#
#3230000
1#
#3240000
0#
#3250000
1#
#3260000
0#
#3270000
1#
#3280000
0#
#3290000
1#
#3300000
0#
#3310000
1#
#3320000
0#
#3330000
1#
#3340000
b100 3
0#
1&
#3350000
b1100 1
1#
#3360000
0#
0&
#3370000
1#
#3380000
0#
#3390000
1#
#3400000
0#
#3410000
1#
#3420000
0#
#3430000
1#
#3440000
0#
#3450000
1#
#3460000
0#
#3470000
1#
#3480000
0#
#3490000
1#
#3500000
b101 3
0#
1&
#3510000
b1101 1
1#
#3520000
0#
0&
#3530000
1#
#3540000
0#
#3550000
1#
#3560000
0#
#3570000
1#
#3580000
0#
#3590000
1#
#3600000
0#
#3610000
1#
#3620000
0#
#3630000
1#
#3640000
0#
#3650000
1#
#3660000
b110 3
0#
1&
#3670000
b1110 1
1#
#3680000
0#
0&
#3690000
1#
#3700000
0#
#3710000
1#
#3720000
0#
#3730000
1#
#3740000
0#
#3750000
1#
#3760000
0#
#3770000
1#
#3780000
0#
#3790000
1#
#3800000
0#
#3810000
1#
#3820000
b111 3
0#
1&
#3830000
b1111 1
1#
#3840000
0#
0&
#3850000
1#
#3860000
0#
#3870000
1#
#3880000
0#
#3890000
1#
#3900000
0#
#3910000
1#
#3920000
0#
#3930000
1#
#3940000
0#
#3950000
1#
#3960000
0#
#3970000
1#
#3980000
b1000 3
0#
1&
#3990000
b1 +
b10000000 ,
b0 1
1#
#4000000
0#
0&
#4010000
1#
#4020000
0#
#4030000
1#
#4040000
0#
#4050000
1#
#4060000
0#
#4070000
1#
#4080000
0#
#4090000
1#
#4100000
0#
#4110000
1#
#4120000
0#
#4130000
1#
#4140000
b1001 3
0#
1&
#4150000
b1 1
1#
#4160000
0#
0&
#4170000
1#
#4180000
0#
#4190000
1#
#4200000
0#
#4210000
1#
#4220000
0#
#4230000
1#
#4240000
0#
#4250000
1#
#4260000
0#
#4270000
1#
#4280000
0#
#4290000
1#
#4300000
b1010 3
0#
1&
#4310000
b10 1
1#
#4320000
0#
0&
#4330000
1#
#4340000
0#
#4350000
1#
#4360000
0#
#4370000
1#
#4380000
0#
#4390000
1#
#4400000
0#
#4410000
1#
#4420000
0#
#4430000
1#
#4440000
0#
#4450000
1#
#4460000
b1011 3
0#
1&
#4470000
b11 1
1#
#4480000
0#
0&
#4490000
1#
#4500000
0#
#4510000
1#
#4520000
0#
#4530000
1#
#4540000
0#
#4550000
1#
#4560000
0#
#4570000
1#
#4580000
0#
#4590000
1#
#4600000
0#
#4610000
1#
#4620000
b1100 3
0#
1&
#4630000
b100 1
1#
#4640000
0#
0&
#4650000
1#
#4660000
0#
#4670000
1#
#4680000
0#
#4690000
1#
#4700000
0#
#4710000
1#
#4720000
0#
#4730000
1#
#4740000
0#
#4750000
1#
#4760000
0#
#4770000
1#
#4780000
b1101 3
0#
1&
#4790000
b101 1
1#
#4800000
0#
0&
#4810000
1#
#4820000
0#
#4830000
1#
#4840000
0#
#4850000
1#
#4860000
0#
#4870000
1#
#4880000
0#
#4890000
1#
#4900000
0#
#4910000
1#
#4920000
0#
#4930000
1#
#4940000
b1110 3
0#
1&
#4950000
b110 1
1#
#4960000
0#
0&
#4970000
1#
#4980000
0#
#4990000
1#
#5000000
0#
#5010000
1#
#5020000
0#
#5030000
1#
#5040000
0#
#5050000
1#
#5060000
0#
#5070000
1#
#5080000
0#
#5090000
1#
#5100000
b1111 3
0#
1&
#5110000
b111 1
1#
#5120000
0#
0&
#5130000
1#
#5140000
0#
#5150000
1#
#5160000
0#
#5170000
1#
#5180000
0#
#5190000
1#
#5200000
0#
#5210000
1#
#5220000
0#
#5230000
1#
#5240000
0#
#5250000
1#
#5260000
0%
02
b0 3
0#
1&
#5270000
0.
b1000 1
1#
#5280000
0#
0&
#5290000
0/
1#
#5300000
0#
#5310000
1#
#5320000
0#
#5330000
1#
#5340000
0#
#5350000
1#
#5360000
0#
#5370000
1#
#5380000
0#
#5390000
1#
#5400000
0#
#5410000
1#
#5420000
b1 3
0#
1&
#5430000
b1001 1
1#
#5440000
0#
0&
#5450000
1#
#5460000
0#
#5470000
1#
#5480000
0#
#5490000
1#
#5500000
0#
#5510000
1#
#5520000
0#
#5530000
1#
#5540000
0#
#5550000
1#
#5560000
0#
#5570000
1#
#5580000
b10 3
0#
1&
#5590000
b1010 1
1#
#5600000
0#
0&
#5610000
1#
#5620000
0#
#5630000
1#
#5640000
0#
#5650000
1#
#5660000
0#
#5670000
1#
#5680000
0#
#5690000
1#
#5700000
0#
#5710000
1#
#5720000
0#
#5730000
1#
#5740000
b11 3
0#
1&
#5750000
b1011 1
1#
#5760000
0#
0&
#5770000
1#
#5780000
0#
#5790000
1#
#5800000
0#
#5810000
1#
#5820000
0#
#5830000
1#
#5840000
0#
#5850000
1#
#5860000
0#
#5870000
1#
#5880000
0#
#5890000
1#
#5900000
b100 3
0#
1&
#5910000
b1100 1
1#
#5920000
0#
0&
#5930000
1#
#5940000
0#
#5950000
1#
#5960000
0#
#5970000
1#
#5980000
0#
#5990000
1#
#6000000
0#
#6010000
1#
#6020000
0#
#6030000
1#
#6040000
0#
#6050000
1#
#6060000
b101 3
0#
1&
#6070000
b1101 1
1#
#6080000
0#
0&
#6090000
1#
#6100000
0#
#6110000
1#
#6120000
0#
#6130000
1#
#6140000
0#
#6150000
1#
#6160000
0#
#6170000
1#
#6180000
0#
#6190000
1#
#6200000
0#
#6210000
1#
#6220000
b110 3
0#
1&
#6230000
b1110 1
1#
#6240000
0#
0&
#6250000
1#
#6260000
0#
#6270000
1#
#6280000
0#
#6290000
1#
#6300000
0#
#6310000
1#
#6320000
0#
#6330000
1#
#6340000
0#
#6350000
1#
#6360000
0#
#6370000
1#
#6380000
b111 3
0#
1&
#6390000
b1111 1
1#
#6400000
0#
0&
#6410000
1#
#6420000
0#
#6430000
1#
#6440000
0#
#6450000
1#
#6460000
0#
#6470000
1#
#6480000
0#
#6490000
1#
#6500000
0#
#6510000
1#
#6520000
0#
#6530000
1#
#6540000
b1000 3
0#
1&
#6550000
b10 +
b1000000 ,
b0 1
1#
#6560000
0#
0&
#6570000
1#
#6580000
0#
#6590000
1#
#6600000
0#
#6610000
1#
#6620000
0#
#6630000
1#
#6640000
0#
#6650000
1#
#6660000
0#
#6670000
1#
#6680000
0#
#6690000
1#
#6700000
b1001 3
0#
1&
#6710000
b1 1
1#
#6720000
0#
0&
#6730000
1#
#6740000
0#
#6750000
1#
#6760000
0#
#6770000
1#
#6780000
0#
#6790000
1#
#6800000
0#
#6810000
1#
#6820000
0#
#6830000
1#
#6840000
0#
#6850000
1#
#6860000
b1010 3
0#
1&
#6870000
b10 1
1#
#6880000
0#
0&
#6890000
1#
#6900000
0#
#6910000
1#
#6920000
0#
#6930000
1#
#6940000
0#
#6950000
1#
#6960000
0#
#6970000
1#
#6980000
0#
#6990000
1#
#7000000
0#
#7010000
1#
#7020000
b1011 3
0#
1&
#7030000
b11 1
1#
#7040000
0#
0&
#7050000
1#
#7060000
0#
#7070000
1#
#7080000
0#
#7090000
1#
#7100000
0#
#7110000
1#
#7120000
0#
#7130000
1#
#7140000
0#
#7150000
1#
#7160000
0#
#7170000
1#
#7180000
b1100 3
0#
1&
#7190000
b100 1
1#
#7200000
0#
0&
#7210000
1#
#7220000
0#
#7230000
1#
#7240000
0#
#7250000
1#
#7260000
0#
#7270000
1#
#7280000
0#
#7290000
1#
#7300000
0#
#7310000
1#
#7320000
0#
#7330000
1#
#7340000
b1101 3
0#
1&
#7350000
b101 1
1#
#7360000
0#
0&
#7370000
1#
#7380000
0#
#7390000
1#
#7400000
0#
#7410000
1#
#7420000
0#
#7430000
1#
#7440000
0#
#7450000
1#
#7460000
0#
#7470000
1#
#7480000
0#
#7490000
1#
#7500000
b1110 3
0#
1&
#7510000
b110 1
1#
#7520000
0#
0&
#7530000
1#
#7540000
0#
#7550000
1#
#7560000
0#
#7570000
1#
#7580000
0#
#7590000
1#
#7600000
0#
#7610000
1#
#7620000
0#
#7630000
1#
#7640000
0#
#7650000
1#
#7660000
b1111 3
0#
1&
#7670000
b111 1
1#
#7680000
0#
0&
#7690000
1#
#7700000
0#
#7710000
1#
#7720000
0#
#7730000
1#
#7740000
0#
#7750000
1#
#7760000
0#
#7770000
1#
#7780000
0#
#7790000
1#
#7800000
0#
#7810000
1#
#7820000
b0 3
0#
1&
#7830000
b1000 1
1#
#7840000
0#
0&
#7850000
1#
#7860000
0#
#7870000
1#
#7880000
0#
#7890000
1#
#7900000
0#
#7910000
1#
#7920000
0#
#7930000
1#
#7940000
0#
#7950000
1#
#7960000
0#
#7970000
1#
#7980000
b1 3
0#
1&
#7990000
b1001 1
1#
#8000000
0#
0&
#8010000
1#
#8020000
0#
#8030000
1#
#8040000
0#
#8050000
1#
#8060000
0#
#8070000
1#
#8080000
0#
#8090000
1#
#8100000
0#
#8110000
1#
#8120000
0#
#8130000
1#
#8140000
b10 3
0#
1&
#8150000
b1010 1
1#
#8160000
0#
0&
#8170000
1#
#8180000
0#
#8190000
1#
#8200000
0#
#8210000
1#
#8220000
0#
#8230000
1#
#8240000
0#
#8250000
1#
#8260000
0#
#8270000
1#
#8280000
0#
#8290000
1#
#8300000
b11 3
0#
1&
#8310000
b1011 1
1#
#8320000
0#
0&
#8330000
1#
#8340000
0#
#8350000
1#
#8360000
0#
#8370000
1#
#8380000
0#
#8390000
1#
#8400000
0#
#8410000
1#
#8420000
0#
#8430000
1#
#8440000
0#
#8450000
1#
#8460000
b100 3
0#
1&
#8470000
b1100 1
1#
#8480000
0#
0&
#8490000
1#
#8500000
0#
#8510000
1#
#8520000
0#
#8530000
1#
#8540000
0#
#8550000
1#
#8560000
0#
#8570000
1#
#8580000
0#
#8590000
1#
#8600000
0#
#8610000
1#
#8620000
b101 3
0#
1&
#8630000
b1101 1
1#
#8640000
0#
0&
#8650000
1#
#8660000
0#
#8670000
1#
#8680000
0#
#8690000
1#
#8700000
0#
#8710000
1#
#8720000
0#
#8730000
1#
#8740000
0#
#8750000
1#
#8760000
0#
#8770000
1#
#8780000
b110 3
0#
1&
#8790000
b1110 1
1#
#8800000
0#
0&
#8810000
1#
#8820000
0#
#8830000
1#
#8840000
0#
#8850000
1#
#8860000
0#
#8870000
1#
#8880000
0#
#8890000
1#
#8900000
0#
#8910000
1#
#8920000
0#
#8930000
1#
#8940000
b111 3
0#
1&
#8950000
b1111 1
1#
#8960000
0#
0&
#8970000
1#
#8980000
0#
#8990000
1#
#9000000
0#
#9010000
1#
#9020000
0#
#9030000
1#
#9040000
0#
#9050000
1#
#9060000
0#
#9070000
1#
#9080000
0#
#9090000
1#
#9100000
b1000 3
0#
1&
#9110000
b11 +
b100000 ,
b0 1
1#
#9120000
0#
0&
#9130000
1#
#9140000
0#
#9150000
1#
#9160000
0#
#9170000
1#
#9180000
0#
#9190000
1#
#9200000
0#
#9210000
1#
#9220000
0#
#9230000
1#
#9240000
0#
#9250000
1#
#9260000
b1001 3
0#
1&
#9270000
b1 1
1#
#9280000
0#
0&
#9290000
1#
#9300000
0#
#9310000
1#
#9320000
0#
#9330000
1#
#9340000
0#
#9350000
1#
#9360000
0#
#9370000
1#
#9380000
0#
#9390000
1#
#9400000
0#
#9410000
1#
#9420000
b1010 3
0#
1&
#9430000
b10 1
1#
#9440000
0#
0&
#9450000
1#
#9460000
0#
#9470000
1#
#9480000
0#
#9490000
1#
#9500000
0#
#9510000
1#
#9520000
0#
#9530000
1#
#9540000
0#
#9550000
1#
#9560000
0#
#9570000
1#
#9580000
b1011 3
0#
1&
#9590000
b11 1
1#
#9600000
0#
0&
#9610000
1#
#9620000
0#
#9630000
1#
#9640000
0#
#9650000
1#
#9660000
0#
#9670000
1#
#9680000
0#
#9690000
1#
#9700000
0#
#9710000
1#
#9720000
0#
#9730000
1#
#9740000
b1100 3
0#
1&
#9750000
b100 1
1#
#9760000
0#
0&
#9770000
1#
#9780000
0#
#9790000
1#
#9800000
0#
#9810000
1#
#9820000
0#
#9830000
1#
#9840000
0#
#9850000
1#
#9860000
0#
#9870000
1#
#9880000
0#
#9890000
1#
#9900000
b1101 3
0#
1&
#9910000
b101 1
1#
#9920000
0#
0&
#9930000
1#
#9940000
0#
#9950000
1#
#9960000
0#
#9970000
1#
#9980000
0#
#9990000
1#
#10000000
0#
#10010000
1#
#10020000
0#
#10030000
1#
#10040000
0#
#10050000
1#
#10060000
b1110 3
0#
1&
#10070000
b110 1
1#
#10080000
0#
0&
#10090000
1#
#10100000
0#
#10110000
1#
#10120000
0#
#10130000
1#
#10140000
0#
#10150000
1#
#10160000
0#
#10170000
1#
#10180000
0#
#10190000
1#
#10200000
0#
#10210000
1#
#10220000
b1111 3
0#
1&
#10230000
b111 1
1#
#10240000
0#
0&
#10250000
1#
#10260000
0#
#10270000
1#
#10280000
0#
#10290000
1#
#10300000
0#
#10310000
1#
#10320000
0#
#10330000
1#
#10340000
0#
#10350000
1#
#10360000
0#
#10370000
1#
#10380000
b0 3
0#
1&
#10390000
b1000 1
1#
#10400000
0#
0&
#10410000
1#
#10420000
0#
#10430000
1#
#10440000
0#
#10450000
1#
#10460000
0#
#10470000
1#
#10480000
0#
#10490000
1#
#10500000
0#
#10510000
1#
#10520000
0#
#10530000
1#
#10540000
b1 3
0#
1&
#10550000
b1001 1
1#
#10560000
0#
0&
#10570000
1#
#10580000
0#
#10590000
1#
#10600000
0#
#10610000
1#
#10620000
0#
#10630000
1#
#10640000
0#
#10650000
1#
#10660000
0#
#10670000
1#
#10680000
0#
#10690000
1#
#10700000
b10 3
0#
1&
#10710000
b1010 1
1#
#10720000
0#
0&
#10730000
1#
#10740000
0#
#10750000
1#
#10760000
0#
#10770000
1#
#10780000
0#
#10790000
1#
#10800000
0#
#10810000
1#
#10820000
0#
#10830000
1#
#10840000
0#
#10850000
1#
#10860000
b11 3
0#
1&
#10870000
b1011 1
1#
#10880000
0#
0&
#10890000
1#
#10900000
0#
#10910000
1#
#10920000
0#
#10930000
1#
#10940000
0#
#10950000
1#
#10960000
0#
#10970000
1#
#10980000
0#
#10990000
1#
#11000000
0#
#11010000
1#
#11020000
b100 3
0#
1&
#11030000
b1100 1
1#
#11040000
0#
0&
#11050000
1#
#11060000
0#
#11070000
1#
#11080000
0#
#11090000
1#
#11100000
0#
#11110000
1#
#11120000
0#
#11130000
1#
#11140000
0#
#11150000
1#
#11160000
0#
#11170000
1#
#11180000
b101 3
0#
1&
#11190000
b1101 1
1#
#11200000
0#
0&
#11210000
1#
#11220000
0#
#11230000
1#
#11240000
0#
#11250000
1#
#11260000
0#
#11270000
1#
#11280000
0#
#11290000
1#
#11300000
0#
#11310000
1#
#11320000
0#
#11330000
1#
#11340000
b110 3
0#
1&
#11350000
b1110 1
1#
#11360000
0#
0&
#11370000
1#
#11380000
0#
#11390000
1#
#11400000
0#
#11410000
1#
#11420000
0#
#11430000
1#
#11440000
0#
#11450000
1#
#11460000
0#
#11470000
1#
#11480000
0#
#11490000
1#
#11500000
b111 3
0#
1&
#11510000
b1111 1
1#
#11520000
0#
0&
#11530000
1#
#11540000
0#
#11550000
1#
#11560000
0#
#11570000
1#
#11580000
0#
#11590000
1#
#11600000
0#
#11610000
1#
#11620000
0#
#11630000
1#
#11640000
0#
#11650000
1#
#11660000
b1000 3
0#
1&
#11670000
b100 +
b10000 ,
b0 1
1#
#11680000
0#
0&
#11690000
1#
#11700000
0#
#11710000
1#
#11720000
0#
#11730000
1#
#11740000
0#
#11750000
1#
#11760000
0#
#11770000
1#
#11780000
0#
#11790000
1#
#11800000
0#
#11810000
1#
#11820000
b1001 3
0#
1&
#11830000
b1 1
1#
#11840000
0#
0&
#11850000
1#
#11860000
0#
#11870000
1#
#11880000
0#
#11890000
1#
#11900000
0#
#11910000
1#
#11920000
0#
#11930000
1#
#11940000
0#
#11950000
1#
#11960000
0#
#11970000
1#
#11980000
b1010 3
0#
1&
#11990000
b10 1
1#
#12000000
0#
0&
#12010000
1#
#12020000
0#
#12030000
1#
#12040000
0#
#12050000
1#
#12060000
0#
#12070000
1#
#12080000
0#
#12090000
1#
#12100000
0#
#12110000
1#
#12120000
0#
#12130000
1#
#12140000
b1011 3
0#
1&
#12150000
b11 1
1#
#12160000
0#
0&
#12170000
1#
#12180000
0#
#12190000
1#
#12200000
0#
#12210000
1#
#12220000
0#
#12230000
1#
#12240000
0#
#12250000
1#
#12260000
0#
#12270000
1#
#12280000
0#
#12290000
1#
#12300000
b1100 3
0#
1&
#12310000
b100 1
1#
#12320000
0#
0&
#12330000
1#
#12340000
0#
#12350000
1#
#12360000
0#
#12370000
1#
#12380000
0#
#12390000
1#
#12400000
0#
#12410000
1#
#12420000
0#
#12430000
1#
#12440000
0#
#12450000
1#
#12460000
b1101 3
0#
1&
#12470000
b101 1
1#
#12480000
0#
0&
#12490000
1#
#12500000
0#
#12510000
1#
#12520000
0#
#12530000
1#
#12540000
0#
#12550000
1#
#12560000
0#
#12570000
1#
#12580000
0#
#12590000
1#
#12600000
0#
#12610000
1#
#12620000
b1110 3
0#
1&
#12630000
b110 1
1#
#12640000
0#
0&
#12650000
1#
#12660000
0#
#12670000
1#
#12680000
0#
#12690000
1#
#12700000
0#
#12710000
1#
#12720000
0#
#12730000
1#
#12740000
0#
#12750000
1#
#12760000
0#
#12770000
1#
#12780000
b1111 3
0#
1&
#12790000
b111 1
1#
#12800000
0#
0&
#12810000
1#
#12820000
0#
#12830000
1#
#12840000
0#
#12850000
1#
#12860000
0#
#12870000
1#
#12880000
0#
#12890000
1#
#12900000
0#
#12910000
1#
#12920000
0#
#12930000
1#
#12940000
b0 3
0#
1&
#12950000
b1000 1
1#
#12960000
0#
0&
#12970000
1#
#12980000
0#
#12990000
1#
#13000000
0#
#13010000
1#
#13020000
0#
#13030000
1#
#13040000
0#
#13050000
1#
#13060000
0#
#13070000
1#
#13080000
0#
#13090000
1#
#13100000
b1 3
0#
1&
#13110000
b1001 1
1#
#13120000
0#
0&
#13130000
1#
#13140000
0#
#13150000
1#
#13160000
0#
#13170000
1#
#13180000
0#
#13190000
1#
#13200000
0#
#13210000
1#
#13220000
0#
#13230000
1#
#13240000
0#
#13250000
1#
#13260000
b10 3
0#
1&
#13270000
b1010 1
1#
#13280000
0#
0&
#13290000
1#
#13300000
0#
#13310000
1#
