rtl/uart_tx.v
/*

Title: UART TX module
Designer: AFIR Hachemi
Affiliation: University of Blida 1 - CDTA

UART Information:
  Baudrate: 115200
  Frame shape: 1'b start | 8'b data LSB first | 1'b stop
  Parity: N/A
*/

module uart_tx (
  input wire clk,
  input wire rst,
  input wire [7:0] data_in,
  input wire start,

  output reg busy,
  output reg serial_out
);


localparam IDLE = 2'b00;
localparam START = 2'b01;
localparam DATA = 2'b10;
localparam STOP = 2'b11;

reg [1:0] state;
reg [1:0] next_state;

reg [2:0] bit_count;
reg [7:0] data_reg;

always @(posedge clk or negedge rst) begin
  if (!rst) begin
    state <= IDLE;
    data_reg <= 8'b0;
    bit_count <= 3'b0;
  end
  else begin
    state <= next_state;
    if (state == IDLE && start) begin
      data_reg <= data_in;
      bit_count <= 3'b0;
    end
    else if (state == DATA) begin
      bit_count <= bit_count + 1'b1;
      data_reg <= data_reg >> 1;
    end
  end
end

always @(*) begin

  busy = (state != IDLE);

  case (state)

    IDLE: begin
      serial_out = 1'b1;
      if (start)
        next_state = START;
      else
        next_state = IDLE;
    end

    START: begin
      serial_out = 1'b0;
      next_state = DATA;
    end

    DATA: begin
      serial_out = data_reg[0];
      if (bit_count == 3'd7)
        next_state = STOP;
      else
        next_state = DATA;
    end

    STOP: begin
      serial_out = 1'b1;
      next_state = IDLE;
    end

    default: begin
      serial_out = 1'b1;
      next_state = IDLE;
    end

  endcase

end

endmodule

testbenches/uart_tx_tb.v
`timescale 1ns/1ps

module uart_tx_tb;

  reg clk;
  reg rst;
  reg [7:0] data_in;
  reg start;

  wire busy;
  wire serial_out;

  uart_tx dut(
    .clk(clk),
    .rst(rst),
    .data_in(data_in),
    .start(start),
    .busy(busy),
    .serial_out(serial_out)
  );

always #5 clk = ~clk;

initial begin
  clk = 1'b0;
end 

initial begin

  $dumpfile("sim/uart_tx_tb.vcd");
  $dumpvars(0, uart_tx_tb);

  rst = 1'b0;
  start = 1'b0;
  data_in = 8'b0;

  #20;

  rst = 1'b1;

  data_in = 8'b10110010;
  start = 1'b1;

  #10;
  start = 1'b0;

  #120;

  $finish;

end

endmodule

sim/uart_tx_tb.vcd
$date
	Sat Sep 19 20:35:50 2026
$end
$version
	Icarus Verilog
$end
$timescale
	1ps
$end
$scope module uart_tx_tb $end
$var wire 1 ! serial_out $end
$var wire 1 " busy $end
$var reg 1 # clk $end
$var reg 8 $ data_in [7:0] $end
$var reg 1 % rst $end
$var reg 1 & start $end
$scope module dut $end
$var wire 1 # clk $end
$var wire 8 ' data_in [7:0] $end
$var wire 1 % rst $end
$var wire 1 & start $end
$var parameter 2 ( DATA $end
$var parameter 2 ) IDLE $end
$var parameter 2 * START $end
$var parameter 2 + STOP $end
$var reg 3 , bit_count [2:0] $end
$var reg 1 " busy $end
$var reg 8 - data_reg [7:0] $end
$var reg 2 . next_state [1:0] $end
$var reg 1 ! serial_out $end
$var reg 2 / state [1:0] $end
$upscope $end
$upscope $end
$enddefinitions $end
$comment Show the parameter values. $end
$dumpall
b11 +
b1 *
b0 )
b10 (
$end
#0
$dumpvars
b0 /
b0 .
b0 -
b0 ,
b0 '
0&
0%
b0 $
0#
0"
1!
$end
#5000
1#
#10000
0#
#15000
1#
#20000
b1 .
0#
1&
b10110010 $
b10110010 '
1%
#25000
b10 .
0!
1"
b10110010 -
b1 /
1#
#30000
0#
0&
#35000
b10 /
1#
#40000
0#
#45000
1!
b1011001 -
b1 ,
1#
#50000
0#
#55000
0!
b101100 -
b10 ,
1#
#60000
0#
#65000
b10110 -
b11 ,
1#
#70000
0#
#75000
1!
b1011 -
b100 ,
1#
#80000
0#
#85000
b101 -
b101 ,
1#
#90000
0#
#95000
0!
b10 -
b110 ,
1#
#100000
0#
#105000
b11 .
1!
b1 -
b111 ,
1#
#110000
0#
#115000
b0 .
b0 -
b0 ,
b11 /
1#
#120000
0#
#125000
0"
b0 /
1#
