rtl/uart_tx.v
/*

Title: UART TX module
Designer: AFIR Hachemi
Affiliation: University of Blida 1 - CDTA

UART Information:
  Baudrate: 115200
  Frame shape: 1'b start | 8'b data LSB first | 1'b stop
  Parity: N/A
*/

module uart_tx (
  input wire clk,
  input wire rst,
  input wire tick,
  input wire [7:0] data_in,
  input wire start,

  output reg busy,
  output reg serial_out
);


localparam IDLE = 2'b00;
localparam START = 2'b01;
localparam DATA = 2'b10;
localparam STOP = 2'b11;

reg [1:0] state;
reg [1:0] next_state;

reg [2:0] bit_count;
reg [7:0] data_reg;

reg start_pending;

always @(posedge clk or negedge rst) begin
  if (!rst) begin
    state <= IDLE;
    data_reg <= 8'b0;
    bit_count <= 3'b0;
    start_pending <= 1'b0;
  end

  else begin 

    if (!busy && start && !start_pending) begin 
   
      start_pending <= 1'b1;
      data_reg <= data_in;

    end

    if (tick) begin 
      
      state <= next_state;
      if (state == IDLE && start_pending) begin 

        start_pending <= 1'b0;
        bit_count <= 3'b0;

      end

      else if (state == DATA) begin 

        bit_count <= bit_count + 1'b1;
        data_reg <= data_reg >> 1;

      end 

    end

  end

end

always @(*) begin

  busy = (state != IDLE) || start_pending;

  case (state)

    IDLE: begin
      serial_out = 1'b1;
      if (start_pending)
        next_state = START;
      else
        next_state = IDLE;
    end

    START: begin
      serial_out = 1'b0;
      next_state = DATA;
    end

    DATA: begin
      serial_out = data_reg[0];
      if (bit_count == 3'd7)
        next_state = STOP;
      else
        next_state = DATA;
    end

    STOP: begin
      serial_out = 1'b1;
      next_state = IDLE;
    end

    default: begin
      serial_out = 1'b1;
      next_state = IDLE;
    end

  endcase

end

endmodule

testbenches/uart_tx_tb.v
`timescale 1ns/1ps

module uart_tx_tb;

  reg clk;
  reg rst;
  reg [7:0] data_in;
  reg start;
  reg tick;

  wire busy;
  wire serial_out;

  uart_tx dut(
    .clk(clk),
    .rst(rst),
    .tick(tick),
    .data_in(data_in),
    .start(start),
    .busy(busy),
    .serial_out(serial_out)
  );

integer count;

always #10 clk = ~clk;

always @(posedge clk) begin 
  if (count == 3) begin 
    tick <= 1'b1;
    count <= 0;
  end
  else begin 
    tick <= 1'b0;
    count <= count + 1;
  end
end

initial begin
  clk = 1'b0;
  tick = 1'b0;
  count = 0;
end 

initial begin

  $dumpfile("sim/uart_tx_tb.vcd");
  $dumpvars(0, uart_tx_tb);

  rst = 1'b0;
  start = 1'b0;
  data_in = 8'b0;

  #30;

  rst = 1'b1;

  data_in = 8'b10110010;
  start = 1'b1;

  #10;
  start = 1'b0;

  #1000;

  $finish;

end

endmodule

sim/uart_tx_tb.vcd
$date
	Sun Sep 20 13:35:44 2026
$end
$version
	Icarus Verilog
$end
$timescale
	1ps
$end
$scope module uart_tx_tb $end
$var wire 1 ! serial_out $end
$var wire 1 " busy $end
$var reg 1 # clk $end
$var reg 8 $ data_in [7:0] $end
$var reg 1 % rst $end
$var reg 1 & start $end
$var reg 1 ' tick $end
$var integer 32 ( count [31:0] $end
$scope module dut $end
$var wire 1 # clk $end
$var wire 8 ) data_in [7:0] $end
$var wire 1 % rst $end
$var wire 1 & start $end
$var wire 1 ' tick $end
$var parameter 2 * DATA $end
$var parameter 2 + IDLE $end
$var parameter 2 , START $end
$var parameter 2 - STOP $end
$var reg 3 . bit_count [2:0] $end
$var reg 1 " busy $end
$var reg 8 / data_reg [7:0] $end
$var reg 2 0 next_state [1:0] $end
$var reg 1 ! serial_out $end
$var reg 1 1 start_pending $end
$var reg 2 2 state [1:0] $end
$upscope $end
$upscope $end
$enddefinitions $end
$comment Show the parameter values. $end
$dumpall
b11 -
b1 ,
b0 +
b10 *
$end
#0
$dumpvars
b0 2
01
b0 0
b0 /
b0 .
b0 )
b0 (
0'
0&
0%
b0 $
0#
0"
1!
$end
#10000
b1 (
1#
#20000
0#
#30000
b1 0
1"
b10110010 /
11
b10 (
1#
1&
b10110010 $
b10110010 )
1%
#40000
0#
0&
#50000
b11 (
1#
#60000
0#
#70000
b0 (
1'
1#
#80000
0#
#90000
b10 0
0!
01
b1 2
b1 (
0'
1#
#100000
0#
#110000
b10 (
1#
#120000
0#
#130000
b11 (
1#
#140000
0#
#150000
b0 (
1'
1#
#160000
0#
#170000
b10 2
b1 (
0'
1#
#180000
0#
#190000
b10 (
1#
#200000
0#
#210000
b11 (
1#
#220000
0#
#230000
b0 (
1'
1#
#240000
0#
#250000
1!
b1011001 /
b1 .
b1 (
0'
1#
#260000
0#
#270000
b10 (
1#
#280000
0#
#290000
b11 (
1#
#300000
0#
#310000
b0 (
1'
1#
#320000
0#
#330000
0!
b101100 /
b10 .
b1 (
0'
1#
#340000
0#
#350000
b10 (
1#
#360000
0#
#370000
b11 (
1#
#380000
0#
#390000
b0 (
1'
1#
#400000
0#
#410000
b10110 /
b11 .
b1 (
0'
1#
#420000
0#
#430000
b10 (
1#
#440000
0#
#450000
b11 (
1#
#460000
0#
#470000
b0 (
1'
1#
#480000
0#
#490000
1!
b1011 /
b100 .
b1 (
0'
1#
#500000
0#
#510000
b10 (
1#
#520000
0#
#530000
b11 (
1#
#540000
0#
#550000
b0 (
1'
1#
#560000
0#
#570000
b101 /
b101 .
b1 (
0'
1#
#580000
0#
#590000
b10 (
1#
#600000
0#
#610000
b11 (
1#
#620000
0#
#630000
b0 (
1'
1#
#640000
0#
#650000
0!
b10 /
b110 .
b1 (
0'
1#
#660000
0#
#670000
b10 (
1#
#680000
0#
#690000
b11 (
1#
#700000
0#
#710000
b0 (
1'
1#
#720000
0#
#730000
b11 0
1!
b1 /
b111 .
b1 (
0'
1#
#740000
0#
#750000
b10 (
1#
#760000
0#
#770000
b11 (
1#
#780000
0#
#790000
b0 (
1'
1#
#800000
0#
#810000
b0 0
b0 /
b0 .
b11 2
b1 (
0'
1#
#820000
0#
#830000
b10 (
1#
#840000
0#
#850000
b11 (
1#
#860000
0#
#870000
b0 (
1'
1#
#880000
0#
#890000
0"
b0 2
b1 (
0'
1#
#900000
0#
#910000
b10 (
1#
#920000
0#
#930000
b11 (
1#
#940000
0#
#950000
b0 (
1'
1#
#960000
0#
#970000
b1 (
0'
1#
#980000
0#
#990000
b10 (
1#
#1000000
0#
#1010000
b11 (
1#
#1020000
0#
#1030000
b0 (
1'
1#
