rtl/baud.v
// Baud Rate Generator (16x Oversampling Clock Enable)
module baud #(
    parameter CLK_freq  = 50000000, // 50 MHz default
    parameter BAUD_RATE = 115200    // Target Baud Rate
)(
    input  wire clk,   // System clock
    input  wire rst, // Active-low asynchronous reset
    output wire tick   // 16x Baud tick pulse
);

    // Calculate count threshold M = CLK_freq / (16 * BAUD_RATE)
    localparam M = CLK_freq / (16 * BAUD_RATE);
    localparam COUNTER_WIDTH = $clog2(M);

    reg [COUNTER_WIDTH-1:0] count_reg;

    always @(posedge clk or negedge rst) begin
        if (!rst) 
        begin
            count_reg <= {COUNTER_WIDTH{1'b0}};
        end 
        else begin
            if (count_reg == M - 1)
                count_reg <= {COUNTER_WIDTH{1'b0}};
            else
                count_reg <= count_reg + 1'b1;
        end
    end

    // Tick pulse goes HIGH for exactly one clock period when count reaches M-1
    assign tick = (count_reg == M - 1);

endmodule

rtl/uart_rx.v
/*

Title: UART RX module
Designer: Guerrout adem
Affiliation: University of Blida 1 - CDTA

UART Information:
  Baudrate: 115200
  Frame shape: 1'b start | 8'b data LSB first | 1'b stop
  Parity: N/A
*/



module uart_rx (
   input wire clk,
   input wire rst,
   input wire rx,
   input wire tick,
   output reg [7:0] rx_data,
   output reg rx_done
);
   // states encoding
   localparam IDLE = 2'b00;
   localparam START = 2'b01;
   localparam DATA = 2'b10;
   localparam STOP = 2'b11;
   reg [1:0] state;
   
   //internal counters
   
   reg [3:0] tick_reg;
   reg [2:0] bit_reg;
   reg [7:0] data_reg;
   
   reg rx_sync1 , rx_sync2;
   
   always @(posedge clk or negedge rst )
   begin
   if (!rst) begin 
      rx_sync1 <= 1'b1;
      rx_sync2 <= 1'b1;
   end 
   else begin
      rx_sync1 <=rx;
      rx_sync2 <=rx_sync1;
   end
   end
   
   // FSM State Register & Next State Logic
    always @(posedge clk or negedge rst) begin
        if (!rst) begin
            state    <= IDLE;
            tick_reg <= 4'b0;
            bit_reg  <= 3'b0;
            data_reg <= 8'b0;
            rx_data  <= 8'b0;
            rx_done  <= 1'b0;
        end else begin
            // Default: rx_done is a 1-cycle pulse, so clear it every clock cycle
            rx_done <= 1'b0;

        case (state)
                // IDLE: Wait for start bit
             IDLE: begin
                    if (rx_sync2 == 1'b0) begin
                        state    <= START;
                        tick_reg <= 4'b0;
                    end
                end
                //START: take midpoint of start bit
             START: begin
                    if (tick) begin
                        if (tick_reg == 4'd7) begin
                            state    <= DATA;
                            tick_reg <= 4'b0;
                            bit_reg  <= 3'b0; // Reset bit counter (0 to 7)
                        end else begin
                            tick_reg <= tick_reg + 1'b1;
                        end
                    end
                end

                //DATA: Sample 8 data bits, each 16 ticks 
             DATA: begin
                    if (tick) begin
                        if (tick_reg == 4'd15) begin
                            tick_reg <= 4'b0;
                            
                            // Shift incoming bit into MSB (LSB received first)
                            data_reg <= {rx_sync2, data_reg[7:1]};

                            if (bit_reg == 3'd7) begin
                                state <= STOP; // Received all 8 bits
                            end else begin
                                bit_reg <= bit_reg + 1'b1;
                            end
                        end else begin
                            tick_reg <= tick_reg + 1'b1;
                        end
                    end
                end

                // STOP: Wait 16 ticks for the stop bit
             STOP: begin
                    if (tick) begin
                        if (tick_reg == 4'd15) begin
                            state   <= IDLE;      // Back to IDLE
                            rx_data <= data_reg;  // Output final byte
                            rx_done <= 1'b1;      // Flag data ready!
                        end else begin
                            tick_reg <= tick_reg + 1'b1;
                        end
                    end
                end

                default: state <= IDLE;
            endcase
        end
    end
endmodule

rtl/uart_tx.v
/*

Title: UART TX module
Designer: AFIR Hachemi
Affiliation: University of Blida 1 - CDTA

UART Information:
  Baudrate: 115200
  Frame shape: 1'b start | 8'b data LSB first | 1'b stop
  Parity: N/A
*/

module uart_tx (
  input wire clk,
  input wire rst,
  input wire tick,
  input wire [7:0] data_in,
  input wire start,

  output reg busy,
  output reg serial_out
);


localparam IDLE = 2'b00;
localparam START = 2'b01;
localparam DATA = 2'b10;
localparam STOP = 2'b11;

reg [1:0] state;
reg [1:0] next_state;

reg [2:0] bit_count;
reg [7:0] data_reg;

reg start_pending;

always @(posedge clk or negedge rst) begin
  if (!rst) begin
    state <= IDLE;
    data_reg <= 8'b0;
    bit_count <= 3'b0;
    start_pending <= 1'b0;
  end

  else begin 

    if (!busy && start && !start_pending) begin 
   
      start_pending <= 1'b1;
      data_reg <= data_in;

    end

    if (tick) begin 
      
      state <= next_state;
      if (state == IDLE && start_pending) begin 

        start_pending <= 1'b0;
        bit_count <= 3'b0;

      end

      else if (state == DATA) begin 

        bit_count <= bit_count + 1'b1;
        data_reg <= data_reg >> 1;

      end 

    end

  end

end

always @(*) begin

  busy = (state != IDLE) || start_pending;

  case (state)

    IDLE: begin
      serial_out = 1'b1;
      if (start_pending)
        next_state = START;
      else
        next_state = IDLE;
    end

    START: begin
      serial_out = 1'b0;
      next_state = DATA;
    end

    DATA: begin
      serial_out = data_reg[0];
      if (bit_count == 3'd7)
        next_state = STOP;
      else
        next_state = DATA;
    end

    STOP: begin
      serial_out = 1'b1;
      next_state = IDLE;
    end

    default: begin
      serial_out = 1'b1;
      next_state = IDLE;
    end

  endcase

end

endmodule

rtl/uart_top.v
/*

Title: UART top module
Designer: AFIR Hachemi
Affiliation: University of Blida 1 - CDTA

UART Information:
  Baudrate: 115200
  Frame shape: 1'b start | 8'b data LSB first | 1'b stop
  Parity: N/A
*/

module uart_top (

  input wire clk,
  input wire rst,
  input wire [7:0] tx_in,
  input wire rx_in,
  input wire start,

  output wire [7:0] rx_out,
  output wire tx_out,

  output wire busy,
  output wire rx_done

);

  wire tick;

  uart_tx u_uart_tx (
    .clk (clk),
    .rst (rst),
    .tick (tick),
    .data_in (tx_in),
    .start (start),
    .busy (busy),
    .serial_out (tx_out)
  );

  uart_rx u_uart_rx (
    .clk (clk),
    .rst (rst),
    .tick (tick),
    .rx (rx_in),
    .rx_data (rx_out),
    .rx_done (rx_done)
  );

  baud u_baud_gen (
    .clk (clk),
    .rst (rst),
    .tick (tick)
  );
  
endmodule

testbenches/uart_top_tb.v
`timescale 1ns/1ps

module uart_top_tb;

  reg clk;
  reg rst;
  reg [7:0] tx_in;
  wire rx_in;
  reg start;

  wire [7:0] rx_out;
  wire rx_done;

  wire tx_out;
  wire busy;

  always #10 clk = ~clk;

  assign rx_in = tx_out;

  uart_top uut (
      .clk (clk),
      .rst (rst),
      .tx_in (tx_in),
      .rx_in (rx_in),
      .start (start),
      .rx_out (rx_out),
      .rx_done (rx_done),
      .tx_out (tx_out),
      .busy (busy)
  );

  initial begin 
    clk = 1'b0;
    rst = 1'b0;
    tx_in = 8'b0;
    start = 1'b0;
  end

  initial begin

  $dumpfile("sim/uart_top_tb.vcd");
  $dumpvars(0, uart_top_tb);

  #25;

  rst = 1'b1;

  tx_in = 8'b10110010;
  start = 1'b1;

  #10;
  start = 1'b0;

  #100_000;

  if (rx_out == 8'b10110010)
    $display("PASS: RX received 10110010");

  else
    $display("FAIL: RX = %b, rx_done = %b", rx_out, rx_done);


  rst = 1'b0;
  tx_in = 8'b0;

  #100;

  $finish;

  end

endmodule

sim/uart_top_tb.vcd
$date
	Sun Sep 20 19:11:00 2026
$end
$version
	Icarus Verilog
$end
$timescale
	1ps
$end
$scope module uart_top_tb $end
$var wire 1 ! rx_in $end
$var wire 1 " tx_out $end
$var wire 8 # rx_out [7:0] $end
$var wire 1 $ rx_done $end
$var wire 1 % busy $end
$var reg 1 & clk $end
$var reg 1 ' rst $end
$var reg 1 ( start $end
$var reg 8 ) tx_in [7:0] $end
$scope module uut $end
$var wire 1 & clk $end
$var wire 1 ' rst $end
$var wire 1 ! rx_in $end
$var wire 1 ( start $end
$var wire 8 * tx_in [7:0] $end
$var wire 1 " tx_out $end
$var wire 1 + tick $end
$var wire 8 , rx_out [7:0] $end
$var wire 1 $ rx_done $end
$var wire 1 % busy $end
$scope module u_baud_gen $end
$var wire 1 & clk $end
$var wire 1 ' rst $end
$var wire 1 + tick $end
$var parameter 32 - BAUD_RATE $end
$var parameter 32 . CLK_freq $end
$var parameter 32 / COUNTER_WIDTH $end
$var parameter 64 0 M $end
$var reg 5 1 count_reg [4:0] $end
$upscope $end
$scope module u_uart_rx $end
$var wire 1 & clk $end
$var wire 1 ' rst $end
$var wire 1 ! rx $end
$var wire 1 + tick $end
$var parameter 2 2 DATA $end
$var parameter 2 3 IDLE $end
$var parameter 2 4 START $end
$var parameter 2 5 STOP $end
$var reg 3 6 bit_reg [2:0] $end
$var reg 8 7 data_reg [7:0] $end
$var reg 8 8 rx_data [7:0] $end
$var reg 1 $ rx_done $end
$var reg 1 9 rx_sync1 $end
$var reg 1 : rx_sync2 $end
$var reg 2 ; state [1:0] $end
$var reg 4 < tick_reg [3:0] $end
$upscope $end
$scope module u_uart_tx $end
$var wire 1 & clk $end
$var wire 8 = data_in [7:0] $end
$var wire 1 ' rst $end
$var wire 1 ( start $end
$var wire 1 + tick $end
$var parameter 2 > DATA $end
$var parameter 2 ? IDLE $end
$var parameter 2 @ START $end
$var parameter 2 A STOP $end
$var reg 3 B bit_count [2:0] $end
$var reg 1 % busy $end
$var reg 8 C data_reg [7:0] $end
$var reg 2 D next_state [1:0] $end
$var reg 1 " serial_out $end
$var reg 1 E start_pending $end
$var reg 2 F state [1:0] $end
$upscope $end
$upscope $end
$upscope $end
$enddefinitions $end
$comment Show the parameter values. $end
$dumpall
b11 A
b1 @
b0 ?
b10 >
b11 5
b1 4
b0 3
b10 2
b11011 0
b101 /
b10111110101111000010000000 .
b11100001000000000 -
$end
#0
$dumpvars
b0 F
0E
b0 D
b0 C
b0 B
b0 =
b0 <
b0 ;
1:
19
b0 8
b0 7
b0 6
b0 1
b0 ,
0+
b0 *
b0 )
0(
0'
0&
0%
0$
b0 #
1"
1!
$end
#10000
1&
#20000
0&
#25000
1(
b10110010 )
b10110010 *
b10110010 =
1'
#30000
b1 D
1%
b10110010 C
1E
b1 1
1&
#35000
0(
#40000
0&
#50000
b10 1
1&
#60000
0&
#70000
b11 1
1&
#80000
0&
#90000
b100 1
1&
#100000
0&
#110000
b101 1
1&
#120000
0&
#130000
b110 1
1&
#140000
0&
#150000
b111 1
1&
#160000
0&
#170000
b1000 1
1&
#180000
0&
#190000
b1001 1
1&
#200000
0&
#210000
b1010 1
1&
#220000
0&
#230000
b1011 1
1&
#240000
0&
#250000
b1100 1
1&
#260000
0&
#270000
b1101 1
1&
#280000
0&
#290000
b1110 1
1&
#300000
0&
#310000
b1111 1
1&
#320000
0&
#330000
b10000 1
1&
#340000
0&
#350000
b10001 1
1&
#360000
0&
#370000
b10010 1
1&
#380000
0&
#390000
b10011 1
1&
#400000
0&
#410000
b10100 1
1&
#420000
0&
#430000
b10101 1
1&
#440000
0&
#450000
b10110 1
1&
#460000
0&
#470000
b10111 1
1&
#480000
0&
#490000
b11000 1
1&
#500000
0&
#510000
b11001 1
1&
#520000
0&
#530000
1+
b11010 1
1&
#540000
0&
#550000
b10 D
0!
0"
0+
0E
b1 F
b0 1
1&
#560000
0&
#570000
b1 1
09
1&
#580000
0&
#590000
0:
b10 1
1&
#600000
0&
#610000
b11 1
b1 ;
1&
#620000
0&
#630000
b100 1
1&
#640000
0&
#650000
b101 1
1&
#660000
0&
#670000
b110 1
1&
#680000
0&
#690000
b111 1
1&
#700000
0&
#710000
b1000 1
1&
#720000
0&
#730000
b1001 1
1&
#740000
0&
#750000
b1010 1
1&
#760000
0&
#770000
b1011 1
1&
#780000
0&
#790000
b1100 1
1&
#800000
0&
#810000
b1101 1
1&
#820000
0&
#830000
b1110 1
1&
#840000
0&
#850000
b1111 1
1&
#860000
0&
#870000
b10000 1
1&
#880000
0&
#890000
b10001 1
1&
#900000
0&
#910000
b10010 1
1&
#920000
0&
#930000
b10011 1
1&
#940000
0&
#950000
b10100 1
1&
#960000
0&
#970000
b10101 1
1&
#980000
0&
#990000
b10110 1
1&
#1000000
0&
#1010000
b10111 1
1&
#1020000
0&
#1030000
b11000 1
1&
#1040000
0&
#1050000
b11001 1
1&
#1060000
0&
#1070000
1+
b11010 1
1&
#1080000
0&
#1090000
0+
b0 1
b1 <
b10 F
1&
#1100000
0&
#1110000
b1 1
1&
#1120000
0&
#1130000
b10 1
1&
#1140000
0&
#1150000
b11 1
1&
#1160000
0&
#1170000
b100 1
1&
#1180000
0&
#1190000
b101 1
1&
#1200000
0&
#1210000
b110 1
1&
#1220000
0&
#1230000
b111 1
1&
#1240000
0&
#1250000
b1000 1
1&
#1260000
0&
#1270000
b1001 1
1&
#1280000
0&
#1290000
b1010 1
1&
#1300000
0&
#1310000
b1011 1
1&
#1320000
0&
#1330000
b1100 1
1&
#1340000
0&
#1350000
b1101 1
1&
#1360000
0&
#1370000
b1110 1
1&
#1380000
0&
#1390000
b1111 1
1&
#1400000
0&
#1410000
b10000 1
1&
#1420000
0&
#1430000
b10001 1
1&
#1440000
0&
#1450000
b10010 1
1&
#1460000
0&
#1470000
b10011 1
1&
#1480000
0&
#1490000
b10100 1
1&
#1500000
0&
#1510000
b10101 1
1&
#1520000
0&
#1530000
b10110 1
1&
#1540000
0&
#1550000
b10111 1
1&
#1560000
0&
#1570000
b11000 1
1&
#1580000
0&
#1590000
b11001 1
1&
#1600000
0&
#1610000
1+
b11010 1
1&
#1620000
0&
#1630000
1!
1"
0+
b1011001 C
b1 B
b10 <
b0 1
1&
#1640000
0&
#1650000
b1 1
19
1&
#1660000
0&
#1670000
1:
b10 1
1&
#1680000
0&
#1690000
b11 1
1&
#1700000
0&
#1710000
b100 1
1&
#1720000
0&
#1730000
b101 1
1&
#1740000
0&
#1750000
b110 1
1&
#1760000
0&
#1770000
b111 1
1&
#1780000
0&
#1790000
b1000 1
1&
#1800000
0&
#1810000
b1001 1
1&
#1820000
0&
#1830000
b1010 1
1&
#1840000
0&
#1850000
b1011 1
1&
#1860000
0&
#1870000
b1100 1
1&
#1880000
0&
#1890000
b1101 1
1&
#1900000
0&
#1910000
b1110 1
1&
#1920000
0&
#1930000
b1111 1
1&
#1940000
0&
#1950000
b10000 1
1&
#1960000
0&
#1970000
b10001 1
1&
#1980000
0&
#1990000
b10010 1
1&
#2000000
0&
#2010000
b10011 1
1&
#2020000
0&
#2030000
b10100 1
1&
#2040000
0&
#2050000
b10101 1
1&
#2060000
0&
#2070000
b10110 1
1&
#2080000
0&
#2090000
b10111 1
1&
#2100000
0&
#2110000
b11000 1
1&
#2120000
0&
#2130000
b11001 1
1&
#2140000
0&
#2150000
1+
b11010 1
1&
#2160000
0&
#2170000
0+
0!
0"
b0 1
b11 <
b101100 C
b10 B
1&
#2180000
0&
#2190000
09
b1 1
1&
#2200000
0&
#2210000
b10 1
0:
1&
#2220000
0&
#2230000
b11 1
1&
#2240000
0&
#2250000
b100 1
1&
#2260000
0&
#2270000
b101 1
1&
#2280000
0&
#2290000
b110 1
1&
#2300000
0&
#2310000
b111 1
1&
#2320000
0&
#2330000
b1000 1
1&
#2340000
0&
#2350000
b1001 1
1&
#2360000
0&
#2370000
b1010 1
1&
#2380000
0&
#2390000
b1011 1
1&
#2400000
0&
#2410000
b1100 1
1&
#2420000
0&
#2430000
b1101 1
1&
#2440000
0&
#2450000
b1110 1
1&
#2460000
0&
#2470000
b1111 1
1&
#2480000
0&
#2490000
b10000 1
1&
#2500000
0&
#2510000
b10001 1
1&
#2520000
0&
#2530000
b10010 1
1&
#2540000
0&
#2550000
b10011 1
1&
#2560000
0&
#2570000
b10100 1
1&
#2580000
0&
#2590000
b10101 1
1&
#2600000
0&
#2610000
b10110 1
1&
#2620000
0&
#2630000
b10111 1
1&
#2640000
0&
#2650000
b11000 1
1&
#2660000
0&
#2670000
b11001 1
1&
#2680000
0&
#2690000
1+
b11010 1
1&
#2700000
0&
#2710000
0+
b10110 C
b11 B
b100 <
b0 1
1&
#2720000
0&
#2730000
b1 1
1&
#2740000
0&
#2750000
b10 1
1&
#2760000
0&
#2770000
b11 1
1&
#2780000
0&
#2790000
b100 1
1&
#2800000
0&
#2810000
b101 1
1&
#2820000
0&
#2830000
b110 1
1&
#2840000
0&
#2850000
b111 1
1&
#2860000
0&
#2870000
b1000 1
1&
#2880000
0&
#2890000
b1001 1
1&
#2900000
0&
#2910000
b1010 1
1&
#2920000
0&
#2930000
b1011 1
1&
#2940000
0&
#2950000
b1100 1
1&
#2960000
0&
#2970000
b1101 1
1&
#2980000
0&
#2990000
b1110 1
1&
#3000000
0&
#3010000
b1111 1
1&
#3020000
0&
#3030000
b10000 1
1&
#3040000
0&
#3050000
b10001 1
1&
#3060000
0&
#3070000
b10010 1
1&
#3080000
0&
#3090000
b10011 1
1&
#3100000
0&
#3110000
b10100 1
1&
#3120000
0&
#3130000
b10101 1
1&
#3140000
0&
#3150000
b10110 1
1&
#3160000
0&
#3170000
b10111 1
1&
#3180000
0&
#3190000
b11000 1
1&
#3200000
0&
#3210000
b11001 1
1&
#3220000
0&
#3230000
1+
b11010 1
1&
#3240000
0&
#3250000
0+
1!
1"
b0 1
b101 <
b1011 C
b100 B
1&
#3260000
0&
#3270000
19
b1 1
1&
#3280000
0&
#3290000
b10 1
1:
1&
#3300000
0&
#3310000
b11 1
1&
#3320000
0&
#3330000
b100 1
1&
#3340000
0&
#3350000
b101 1
1&
#3360000
0&
#3370000
b110 1
1&
#3380000
0&
#3390000
b111 1
1&
#3400000
0&
#3410000
b1000 1
1&
#3420000
0&
#3430000
b1001 1
1&
#3440000
0&
#3450000
b1010 1
1&
#3460000
0&
#3470000
b1011 1
1&
#3480000
0&
#3490000
b1100 1
1&
#3500000
0&
#3510000
b1101 1
1&
#3520000
0&
#3530000
b1110 1
1&
#3540000
0&
#3550000
b1111 1
1&
#3560000
0&
#3570000
b10000 1
1&
#3580000
0&
#3590000
b10001 1
1&
#3600000
0&
#3610000
b10010 1
1&
#3620000
0&
#3630000
b10011 1
1&
#3640000
0&
#3650000
b10100 1
1&
#3660000
0&
#3670000
b10101 1
1&
#3680000
0&
#3690000
b10110 1
1&
#3700000
0&
#3710000
b10111 1
1&
#3720000
0&
#3730000
b11000 1
1&
#3740000
0&
#3750000
b11001 1
1&
#3760000
0&
#3770000
1+
b11010 1
1&
#3780000
0&
#3790000
0+
b101 C
b101 B
b110 <
b0 1
1&
#3800000
0&
#3810000
b1 1
1&
#3820000
0&
#3830000
b10 1
1&
#3840000
0&
#3850000
b11 1
1&
#3860000
0&
#3870000
b100 1
1&
#3880000
0&
#3890000
b101 1
1&
#3900000
0&
#3910000
b110 1
1&
#3920000
0&
#3930000
b111 1
1&
#3940000
0&
#3950000
b1000 1
1&
#3960000
0&
#3970000
b1001 1
1&
#3980000
0&
#3990000
b1010 1
1&
#4000000
0&
#4010000
b1011 1
1&
#4020000
0&
#4030000
b1100 1
1&
#4040000
0&
#4050000
b1101 1
1&
#4060000
0&
#4070000
b1110 1
1&
#4080000
0&
#4090000
b1111 1
1&
#4100000
0&
#4110000
b10000 1
1&
#4120000
0&
#4130000
b10001 1
1&
#4140000
0&
#4150000
b10010 1
1&
#4160000
0&
#4170000
b10011 1
1&
#4180000
0&
#4190000
b10100 1
1&
#4200000
0&
#4210000
b10101 1
1&
#4220000
0&
#4230000
b10110 1
1&
#4240000
0&
#4250000
b10111 1
1&
#4260000
0&
#4270000
b11000 1
1&
#4280000
0&
#4290000
b11001 1
1&
#4300000
0&
#4310000
1+
b11010 1
1&
#4320000
0&
#4330000
0+
0!
0"
b0 1
b111 <
b10 C
b110 B
1&
#4340000
0&
#4350000
09
b1 1
1&
#4360000
0&
#4370000
b10 1
0:
1&
#4380000
0&
#4390000
b11 1
1&
#4400000
0&
#4410000
b100 1
1&
#4420000
0&
#4430000
b101 1
1&
#4440000
0&
#4450000
b110 1
1&
#4460000
0&
#4470000
b111 1
1&
#4480000
0&
#4490000
b1000 1
1&
#4500000
0&
#4510000
b1001 1
1&
#4520000
0&
#4530000
b1010 1
1&
#4540000
0&
#4550000
b1011 1
1&
#4560000
0&
#4570000
b1100 1
1&
#4580000
0&
#4590000
b1101 1
1&
#4600000
0&
#4610000
b1110 1
1&
#4620000
0&
#4630000
b1111 1
1&
#4640000
0&
#4650000
b10000 1
1&
#4660000
0&
#4670000
b10001 1
1&
#4680000
0&
#4690000
b10010 1
1&
#4700000
0&
#4710000
b10011 1
1&
#4720000
0&
#4730000
b10100 1
1&
#4740000
0&
#4750000
b10101 1
1&
#4760000
0&
#4770000
b10110 1
1&
#4780000
0&
#4790000
b10111 1
1&
#4800000
0&
#4810000
b11000 1
1&
#4820000
0&
#4830000
b11001 1
1&
#4840000
0&
#4850000
1+
b11010 1
1&
#4860000
0&
#4870000
b11 D
1!
1"
0+
b1 C
b111 B
b0 <
b10 ;
b0 1
1&
#4880000
0&
#4890000
b1 1
19
1&
#4900000
0&
#4910000
1:
b10 1
1&
#4920000
0&
#4930000
b11 1
1&
#4940000
0&
#4950000
b100 1
1&
#4960000
0&
#4970000
b101 1
1&
#4980000
0&
#4990000
b110 1
1&
#5000000
0&
#5010000
b111 1
1&
#5020000
0&
#5030000
b1000 1
1&
#5040000
0&
#5050000
b1001 1
1&
#5060000
0&
#5070000
b1010 1
1&
#5080000
0&
#5090000
b1011 1
1&
#5100000
0&
#5110000
b1100 1
1&
#5120000
0&
#5130000
b1101 1
1&
#5140000
0&
#5150000
b1110 1
1&
#5160000
0&
#5170000
b1111 1
1&
#5180000
0&
#5190000
b10000 1
1&
#5200000
0&
#5210000
b10001 1
1&
#5220000
0&
#5230000
b10010 1
1&
#5240000
0&
#5250000
b10011 1
1&
#5260000
0&
#5270000
b10100 1
1&
#5280000
0&
#5290000
b10101 1
1&
#5300000
0&
#5310000
b10110 1
1&
#5320000
0&
#5330000
b10111 1
1&
#5340000
0&
#5350000
b11000 1
1&
#5360000
0&
#5370000
b11001 1
1&
#5380000
0&
#5390000
1+
b11010 1
1&
#5400000
0&
#5410000
0+
b0 D
b0 1
b1 <
b0 C
b0 B
b11 F
1&
#5420000
0&
#5430000
b1 1
1&
#5440000
0&
#5450000
b10 1
1&
#5460000
0&
#5470000
b11 1
1&
#5480000
0&
#5490000
b100 1
1&
#5500000
0&
#5510000
b101 1
1&
#5520000
0&
#5530000
b110 1
1&
#5540000
0&
#5550000
b111 1
1&
#5560000
0&
#5570000
b1000 1
1&
#5580000
0&
#5590000
b1001 1
1&
#5600000
0&
#5610000
b1010 1
1&
#5620000
0&
#5630000
b1011 1
1&
#5640000
0&
#5650000
b1100 1
1&
#5660000
0&
#5670000
b1101 1
1&
#5680000
0&
#5690000
b1110 1
1&
#5700000
0&
#5710000
b1111 1
1&
#5720000
0&
#5730000
b10000 1
1&
#5740000
0&
#5750000
b10001 1
1&
#5760000
0&
#5770000
b10010 1
1&
#5780000
0&
#5790000
b10011 1
1&
#5800000
0&
#5810000
b10100 1
1&
#5820000
0&
#5830000
b10101 1
1&
#5840000
0&
#5850000
b10110 1
1&
#5860000
0&
#5870000
b10111 1
1&
#5880000
0&
#5890000
b11000 1
1&
#5900000
0&
#5910000
b11001 1
1&
#5920000
0&
#5930000
1+
b11010 1
1&
#5940000
0&
#5950000
0%
0+
b0 F
b10 <
b0 1
1&
#5960000
0&
#5970000
b1 1
1&
#5980000
0&
#5990000
b10 1
1&
#6000000
0&
#6010000
b11 1
1&
#6020000
0&
#6030000
b100 1
1&
#6040000
0&
#6050000
b101 1
1&
#6060000
0&
#6070000
b110 1
1&
#6080000
0&
#6090000
b111 1
1&
#6100000
0&
#6110000
b1000 1
1&
#6120000
0&
#6130000
b1001 1
1&
#6140000
0&
#6150000
b1010 1
1&
#6160000
0&
#6170000
b1011 1
1&
#6180000
0&
#6190000
b1100 1
1&
#6200000
0&
#6210000
b1101 1
1&
#6220000
0&
#6230000
b1110 1
1&
#6240000
0&
#6250000
b1111 1
1&
#6260000
0&
#6270000
b10000 1
1&
#6280000
0&
#6290000
b10001 1
1&
#6300000
0&
#6310000
b10010 1
1&
#6320000
0&
#6330000
b10011 1
1&
#6340000
0&
#6350000
b10100 1
1&
#6360000
0&
#6370000
b10101 1
1&
#6380000
0&
#6390000
b10110 1
1&
#6400000
0&
#6410000
b10111 1
1&
#6420000
0&
#6430000
b11000 1
1&
#6440000
0&
#6450000
b11001 1
1&
#6460000
0&
#6470000
1+
b11010 1
1&
#6480000
0&
#6490000
0+
b0 1
b11 <
1&
#6500000
0&
#6510000
b1 1
1&
#6520000
0&
#6530000
b10 1
1&
#6540000
0&
#6550000
b11 1
1&
#6560000
0&
#6570000
b100 1
1&
#6580000
0&
#6590000
b101 1
1&
#6600000
0&
#6610000
b110 1
1&
#6620000
0&
#6630000
b111 1
1&
#6640000
0&
#6650000
b1000 1
1&
#6660000
0&
#6670000
b1001 1
1&
#6680000
0&
#6690000
b1010 1
1&
#6700000
0&
#6710000
b1011 1
1&
#6720000
0&
#6730000
b1100 1
1&
#6740000
0&
#6750000
b1101 1
1&
#6760000
0&
#6770000
b1110 1
1&
#6780000
0&
#6790000
b1111 1
1&
#6800000
0&
#6810000
b10000 1
1&
#6820000
0&
#6830000
b10001 1
1&
#6840000
0&
#6850000
b10010 1
1&
#6860000
0&
#6870000
b10011 1
1&
#6880000
0&
#6890000
b10100 1
1&
#6900000
0&
#6910000
b10101 1
1&
#6920000
0&
#6930000
b10110 1
1&
#6940000
0&
#6950000
b10111 1
1&
#6960000
0&
#6970000
b11000 1
1&
#6980000
0&
#6990000
b11001 1
1&
#7000000
0&
#7010000
1+
b11010 1
1&
#7020000
0&
#7030000
0+
b100 <
b0 1
1&
#7040000
0&
#7050000
b1 1
1&
#7060000
0&
#7070000
b10 1
1&
#7080000
0&
#7090000
b11 1
1&
#7100000
0&
#7110000
b100 1
1&
#7120000
0&
#7130000
b101 1
1&
#7140000
0&
#7150000
b110 1
1&
#7160000
0&
#7170000
b111 1
1&
#7180000
0&
#7190000
b1000 1
1&
#7200000
0&
#7210000
b1001 1
1&
#7220000
0&
#7230000
b1010 1
1&
#7240000
0&
#7250000
b1011 1
1&
#7260000
0&
#7270000
b1100 1
1&
#7280000
0&
#7290000
b1101 1
1&
#7300000
0&
#7310000
b1110 1
1&
#7320000
0&
#7330000
b1111 1
1&
#7340000
0&
#7350000
b10000 1
1&
#7360000
0&
#7370000
b10001 1
1&
#7380000
0&
#7390000
b10010 1
1&
#7400000
0&
#7410000
b10011 1
1&
#7420000
0&
#7430000
b10100 1
1&
#7440000
0&
#7450000
b10101 1
1&
#7460000
0&
#7470000
b10110 1
1&
#7480000
0&
#7490000
b10111 1
1&
#7500000
0&
#7510000
b11000 1
1&
#7520000
0&
#7530000
b11001 1
1&
#7540000
0&
#7550000
1+
b11010 1
1&
#7560000
0&
#7570000
0+
b0 1
b101 <
1&
#7580000
0&
#7590000
b1 1
1&
#7600000
0&
#7610000
b10 1
1&
#7620000
0&
#7630000
b11 1
1&
#7640000
0&
#7650000
b100 1
1&
#7660000
0&
#7670000
b101 1
1&
#7680000
0&
#7690000
b110 1
1&
#7700000
0&
#7710000
b111 1
1&
#7720000
0&
#7730000
b1000 1
1&
#7740000
0&
#7750000
b1001 1
1&
#7760000
0&
#7770000
b1010 1
1&
#7780000
0&
#7790000
b1011 1
1&
#7800000
0&
#7810000
b1100 1
1&
#7820000
0&
#7830000
b1101 1
1&
#7840000
0&
#7850000
b1110 1
1&
#7860000
0&
#7870000
b1111 1
1&
#7880000
0&
#7890000
b10000 1
1&
#7900000
0&
#7910000
b10001 1
1&
#7920000
0&
#7930000
b10010 1
1&
#7940000
0&
#7950000
b10011 1
1&
#7960000
0&
#7970000
b10100 1
1&
#7980000
0&
#7990000
b10101 1
1&
#8000000
0&
#8010000
b10110 1
1&
#8020000
0&
#8030000
b10111 1
1&
#8040000
0&
#8050000
b11000 1
1&
#8060000
0&
#8070000
b11001 1
1&
#8080000
0&
#8090000
1+
b11010 1
1&
#8100000
0&
#8110000
0+
b110 <
b0 1
1&
#8120000
0&
#8130000
b1 1
1&
#8140000
0&
#8150000
b10 1
1&
#8160000
0&
#8170000
b11 1
1&
#8180000
0&
#8190000
b100 1
1&
#8200000
0&
#8210000
b101 1
1&
#8220000
0&
#8230000
b110 1
1&
#8240000
0&
#8250000
b111 1
1&
#8260000
0&
#8270000
b1000 1
1&
#8280000
0&
#8290000
b1001 1
1&
#8300000
0&
#8310000
b1010 1
1&
#8320000
0&
#8330000
b1011 1
1&
#8340000
0&
#8350000
b1100 1
1&
#8360000
0&
#8370000
b1101 1
1&
#8380000
0&
#8390000
b1110 1
1&
#8400000
0&
#8410000
b1111 1
1&
#8420000
0&
#8430000
b10000 1
1&
#8440000
0&
#8450000
b10001 1
1&
#8460000
0&
#8470000
b10010 1
1&
#8480000
0&
#8490000
b10011 1
1&
#8500000
0&
#8510000
b10100 1
1&
#8520000
0&
#8530000
b10101 1
1&
#8540000
0&
#8550000
b10110 1
1&
#8560000
0&
#8570000
b10111 1
1&
#8580000
0&
#8590000
b11000 1
1&
#8600000
0&
#8610000
b11001 1
1&
#8620000
0&
#8630000
1+
b11010 1
1&
#8640000
0&
#8650000
0+
b0 1
b111 <
1&
#8660000
0&
#8670000
b1 1
1&
#8680000
0&
#8690000
b10 1
1&
#8700000
0&
#8710000
b11 1
1&
#8720000
0&
#8730000
b100 1
1&
#8740000
0&
#8750000
b101 1
1&
#8760000
0&
#8770000
b110 1
1&
#8780000
0&
#8790000
b111 1
1&
#8800000
0&
#8810000
b1000 1
1&
#8820000
0&
#8830000
b1001 1
1&
#8840000
0&
#8850000
b1010 1
1&
#8860000
0&
#8870000
b1011 1
1&
#8880000
0&
#8890000
b1100 1
1&
#8900000
0&
#8910000
b1101 1
1&
#8920000
0&
#8930000
b1110 1
1&
#8940000
0&
#8950000
b1111 1
1&
#8960000
0&
#8970000
b10000 1
1&
#8980000
0&
